CONTRIBUTING.md
README.md
SECURITY.md
admyral/VERSION
admyral/__init__.py
admyral/action.py
admyral/action_registry.py
admyral/actions/__init__.py
admyral/actions/ai_action.py
admyral/actions/controls.py
admyral/actions/dummy_actions.py
admyral/actions/integrations/__init__.py
admyral/actions/integrations/ai/__init__.py
admyral/actions/integrations/ai/anthropic.py
admyral/actions/integrations/ai/azure_openai.py
admyral/actions/integrations/ai/mistralai.py
admyral/actions/integrations/ai/openai.py
admyral/actions/integrations/cases/__init__.py
admyral/actions/integrations/cases/jira.py
admyral/actions/integrations/cases/opsgenie.py
admyral/actions/integrations/cases/pagerduty.py
admyral/actions/integrations/cdr/__init__.py
admyral/actions/integrations/cdr/ms_defender_for_cloud.py
admyral/actions/integrations/cdr/wiz.py
admyral/actions/integrations/cloud/__init__.py
admyral/actions/integrations/cloud/aws.py
admyral/actions/integrations/communication/__init__.py
admyral/actions/integrations/communication/slack.py
admyral/actions/integrations/compliance/__init__.py
admyral/actions/integrations/compliance/github.py
admyral/actions/integrations/compliance/google_drive.py
admyral/actions/integrations/compliance/kandji.py
admyral/actions/integrations/compliance/ms_intune.py
admyral/actions/integrations/compliance/one_password.py
admyral/actions/integrations/compliance/retool.py
admyral/actions/integrations/compliance/zendesk.py
admyral/actions/integrations/database/__init__.py
admyral/actions/integrations/database/db.py
admyral/actions/integrations/edr/__init__.py
admyral/actions/integrations/edr/ms_defender.py
admyral/actions/integrations/edr/sentinel_one.py
admyral/actions/integrations/email/__init__.py
admyral/actions/integrations/email/abnormal_security.py
admyral/actions/integrations/enrich/__init__.py
admyral/actions/integrations/enrich/abuseipdb.py
admyral/actions/integrations/enrich/alienvault_otx.py
admyral/actions/integrations/enrich/greynoise.py
admyral-0.1.43.dist-info/LICENSE
admyral-0.1.43.dist-info/METADATA
admyral-0.1.43.dist-info/WHEEL
admyral-0.1.43.dist-info/entry_points.txt
admyral-0.1.43.dist-info/RECORD
