Metadata-Version: 2.1
Name: admyral
Version: 0.1.43
Summary: 
Author: Daniel Grittner
Author-email: danielgrittner@web.de
Requires-Python: >=3.11,<4.0
Classifier: Programming Language :: Python :: 3
Classifier: Programming Language :: Python :: 3.11
Classifier: Programming Language :: Python :: 3.12
Classifier: Programming Language :: Python :: 3.13
Requires-Dist: aiofiles (>=24.1.0,<25.0.0)
Requires-Dist: aiohttp[speedups] (>=3.9.5,<4.0.0)
Requires-Dist: alembic (>=1.13.2,<2.0.0)
Requires-Dist: anthropic (>=0.31.2,<0.32.0)
Requires-Dist: astor (>=0.8.1,<0.9.0)
Requires-Dist: asyncpg (>=0.29.0,<0.30.0)
Requires-Dist: boto3 (>=1.34.147,<2.0.0)
Requires-Dist: click (>=8.1.7,<9.0.0)
Requires-Dist: cryptography (>=42.0.8,<43.0.0)
Requires-Dist: docker (>=7.1.0,<8.0.0)
Requires-Dist: fastapi (>=0.111.0,<0.112.0)
Requires-Dist: fastapi-nextauth-jwt (>=2.0.0,<3.0.0)
Requires-Dist: google-api-python-client (>=2.149.0,<3.0.0)
Requires-Dist: mistralai (>=0.4.2,<0.5.0)
Requires-Dist: msgraph-sdk (>=1.5.3,<2.0.0)
Requires-Dist: multipledispatch (>=1.0.0,<2.0.0)
Requires-Dist: openai (>=1.37.0,<2.0.0)
Requires-Dist: pip-tools (>=7.4.1,<8.0.0)
Requires-Dist: pre-commit (>=3.8.0,<4.0.0)
Requires-Dist: psutil (>=6.0.0,<7.0.0)
Requires-Dist: psycopg2-binary (>=2.9.9,<3.0.0)
Requires-Dist: pydantic (>=2.7.4,<3.0.0)
Requires-Dist: pydantic-settings (>=2.3.4,<3.0.0)
Requires-Dist: pymysql (>=1.1.1,<2.0.0)
Requires-Dist: python-dateutil (>=2.9.0.post0,<3.0.0)
Requires-Dist: python-dotenv (>=1.0.1,<2.0.0)
Requires-Dist: requests (>=2.32.3,<3.0.0)
Requires-Dist: resend (>=2.2.0,<3.0.0)
Requires-Dist: ruff (>=0.5.5,<0.6.0)
Requires-Dist: setuptools-scm (>=8.1.0,<9.0.0)
Requires-Dist: sqlalchemy[asyncio] (>=2.0.31,<3.0.0)
Requires-Dist: sqlmodel (>=0.0.22,<0.0.23)
Requires-Dist: temporalio (>=1.6.0,<2.0.0)
Requires-Dist: tenacity (>=9.0.0,<10.0.0)
